src/__init__.py
src/cli.py
src/commons/__init__.py
src/commons/globals.py
src/commons/utils.py
src/core/__init__.py
src/core/function_calling.py
src/core/guardrails.py
src/core/utils/__init__.py
src/core/utils/hallucination_utils.py
src/core/utils/model_utils.py
src/main.py
archgw_modelserver-0.3.17.dist-info/METADATA
archgw_modelserver-0.3.17.dist-info/WHEEL
archgw_modelserver-0.3.17.dist-info/entry_points.txt
archgw_modelserver-0.3.17.dist-info/RECORD
