Metadata-Version: 2.4
Name: archgw_modelserver
Version: 0.3.17
Summary: A model server for serving models
License: Apache 2.0
Author: Katanemo Labs, Inc
Author-email: info@katanemo.com
Requires-Python: >=3.10
Classifier: License :: Other/Proprietary License
Classifier: Programming Language :: Python :: 3
Classifier: Programming Language :: Python :: 3.10
Classifier: Programming Language :: Python :: 3.11
Classifier: Programming Language :: Python :: 3.12
Classifier: Programming Language :: Python :: 3.13
Classifier: Programming Language :: Python :: 3.14
Requires-Dist: accelerate (>=1.0.0,<2.0.0)
Requires-Dist: dateparser
Requires-Dist: fastapi (==0.115.0)
Requires-Dist: httpx (==0.27.2)
Requires-Dist: openai (>=1.50.2,<2.0.0)
Requires-Dist: opentelemetry-api (>=1.28.0,<2.0.0)
Requires-Dist: opentelemetry-exporter-otlp (>=1.28.0,<2.0.0)
Requires-Dist: opentelemetry-instrumentation-fastapi (>=0.49b0,<1.0)
Requires-Dist: opentelemetry-sdk (>=1.28.0,<2.0.0)
Requires-Dist: overrides (>=7.7.0,<8.0.0)
Requires-Dist: pydantic (>=2.10.1,<3.0.0)
Requires-Dist: setuptools (==75.5.0)
Requires-Dist: torch (==2.6.0)
Requires-Dist: transformers (>=4.37.0,<5.0.0)
Requires-Dist: uvicorn (==0.31.0)
